tccfriend/__init__.py
tccfriend/tccfriend.py
tccfriend-0.0.2.dist-info/METADATA
tccfriend-0.0.2.dist-info/WHEEL
tccfriend-0.0.2.dist-info/top_level.txt
tccfriend-0.0.2.dist-info/RECORD
